py_youtube_search/__init__.py
py_youtube_search-0.2.3.dist-info/METADATA
py_youtube_search-0.2.3.dist-info/WHEEL
py_youtube_search-0.2.3.dist-info/top_level.txt
py_youtube_search-0.2.3.dist-info/RECORD
