Metadata-Version: 2.4
Name: py-youtube-search
Version: 0.2.3
Summary: A lightweight, regex-based YouTube search library without API keys.
Home-page: https://github.com/VishvaRam/py-youtube-search
Author: VishvaRam
Author-email: murthyvishva@gmail.com
License: MIT
Classifier: Programming Language :: Python :: 3
Classifier: License :: OSI Approved :: MIT License
Classifier: Operating System :: OS Independent
Requires-Python: >=3.6
Requires-Dist: aiohttp>=3.8.0
Dynamic: author
Dynamic: author-email
Dynamic: classifier
Dynamic: description
Dynamic: description-content-type
Dynamic: home-page
Dynamic: license
Dynamic: requires-dist
Dynamic: requires-python
Dynamic: summary
